banana_timer/__init__.py
banana_timer/timer.py
banana_timer-1.0.3.dist-info/METADATA
banana_timer-1.0.3.dist-info/WHEEL
banana_timer-1.0.3.dist-info/top_level.txt
banana_timer-1.0.3.dist-info/RECORD
