Metadata-Version: 2.4
Name: banana_timer
Version: 1.0.3
Summary: A professional countdown Library
Author-email: TheLostIdea1 <afifashamsad.vivo@gmail.com>
Classifier: Programming Language :: Python :: 3
Classifier: License :: OSI Approved :: MIT License
Classifier: Operating System :: OS Independent
Requires-Python: >=3.7
